darklab_utils/__init__.py
darklab_utils-0.0.1.dev3.dist-info/LICENSE
darklab_utils-0.0.1.dev3.dist-info/METADATA
darklab_utils-0.0.1.dev3.dist-info/WHEEL
darklab_utils-0.0.1.dev3.dist-info/top_level.txt
darklab_utils-0.0.1.dev3.dist-info/RECORD
