Metadata-Version: 2.1
Name: darklab-utils
Version: 0.0.1.dev3
Summary: Utility programms
Home-page: https://github.com/darklab8/darklab_utils
Author: dd84ai
Author-email: dd84ai@gmail.com
License: GNU-3
Keywords: utils scripts
Classifier: Development Status :: 3 - Alpha
Classifier: Intended Audience :: Developers
Classifier: Programming Language :: Python
Classifier: Programming Language :: Python :: 3
Classifier: Programming Language :: Python :: 3.10
Requires-Python: >=3.10
License-File: LICENSE
